benchmarks/__init__.py
benchmarks/benchmarks.py
data/tet_mesh.vtu
data/tri_mesh.vtu
docs/.gitignore
docs/Makefile
docs/source/.gitignore
docs/source/1d_profiles_mapper.rst
docs/source/1d_profiles_reader.rst
docs/source/api.rst
docs/source/beam_reader.rst
docs/source/ci_config.rst
docs/source/cli.rst
docs/source/code_style.rst
docs/source/conf.py
docs/source/ggd_reader.rst
docs/source/index.rst
docs/source/installing.rst
docs/source/jorek_reader.rst
docs/source/los_reader.rst
docs/source/position_reader.rst
docs/source/profiles_2d_reader.rst
docs/source/usage.rst
docs/source/wall_limiter_reader.rst
docs/source/_static/imas_paraview.css
docs/source/_templates/custom-class-template.rst
docs/source/_templates/custom-module-template.rst
docs/source/_templates/autosummary/accessor.rst
docs/source/_templates/autosummary/accessor_attribute.rst
docs/source/_templates/autosummary/accessor_callable.rst
docs/source/_templates/autosummary/accessor_method.rst
docs/source/_templates/autosummary/base.rst
docs/source/images/2d_profile_mapped.png
docs/source/images/beam_10m.png
docs/source/images/beam_2m.png
docs/source/images/bezier_options.png
docs/source/images/electron_pressure.png
docs/source/images/filter_icon.png
docs/source/images/ids_dropdown.png
docs/source/images/input_file.png
docs/source/images/input_legacy.png
docs/source/images/input_uri.png
docs/source/images/jorek_bezier_example.png
docs/source/images/los_1.png
docs/source/images/los_1_5.png
docs/source/images/magnetics_positions.png
docs/source/images/mesh.png
docs/source/images/profiles1d_map.png
docs/source/images/profiles_2d.png
docs/source/images/profiles_plot.png
docs/source/images/profiles_plot_options.png
docs/source/images/profiles_psi.png
docs/source/images/psi.png
docs/source/images/rotate_axis.png
docs/source/images/sub_index.png
docs/source/images/wall_limiter.png
imas_paraview/__init__.py
imas_paraview/__main__.py
imas_paraview/_devtools.py
imas_paraview/_ids_util.py
imas_paraview/_version.py
imas_paraview-2.1.0.dist-info/licenses/LICENSE.txt
imas_paraview-2.1.0.dist-info/METADATA
imas_paraview-2.1.0.dist-info/WHEEL
imas_paraview-2.1.0.dist-info/entry_points.txt
imas_paraview-2.1.0.dist-info/top_level.txt
imas_paraview-2.1.0.dist-info/RECORD
