Metadata-Version: 2.4
Name: imas-paraview
Version: 2.1.0
Summary: Tool to convert IMAS Generalized Grid Description (GGD) structures to VTK, together with a few plugins to visualize GGD and non-GGD IMAS data in ParaView.
Author-email: ITER Organization <imas-support@iter.org>
License:                   GNU LESSER GENERAL PUBLIC LICENSE
Project-URL: homepage, https://github.com/iterorganization/IMAS-ParaView
Classifier: Programming Language :: Python :: 3
Classifier: Operating System :: OS Independent
Requires-Python: >=3.8
License-File: LICENSE.txt
Requires-Dist: numpy>=1.19.4
Requires-Dist: vtk>=9.1.0
Requires-Dist: imas-python[netcdf]>=2.0.0
Provides-Extra: all
Requires-Dist: imas_paraview[benchmark,docs,linting,test]; extra == "all"
Provides-Extra: docs
Requires-Dist: sphinx<7.0.0,>=6.0.0; extra == "docs"
Requires-Dist: sphinx-autosummary-accessors>=0.1.2; extra == "docs"
Requires-Dist: sphinx_immaterial<0.12,>=0.11.0; extra == "docs"
Requires-Dist: recommonmark>=0.6; extra == "docs"
Provides-Extra: linting
Requires-Dist: ruff; extra == "linting"
Provides-Extra: test
Requires-Dist: pytest>=6; extra == "test"
Requires-Dist: pytest-cov>=0.6; extra == "test"
Requires-Dist: pytest-xdist; extra == "test"
Requires-Dist: pytest-randomly; extra == "test"
Provides-Extra: benchmark
Requires-Dist: asv==0.6.1; extra == "benchmark"
Requires-Dist: virtualenv; extra == "benchmark"
Dynamic: license-file
